MANIFEST.in
README.rst
pavement.py
paver-minilib.zip
setup.py
neo4j/__init__.py
neo4j/connection.py
neo4j/contextmanager.py
neo4j/cursor.py
neo4j/strings.py
neo4j/test/__init__.py
neo4j/test/performance.py
neo4j/test/test_connection.py
neo4j/test/test_contextmanager.py
neo4j/test/test_cursor.py
neo4j/test/test_exceptions.py
neo4j/test/test_types.py
neo4jdb.egg-info/PKG-INFO
neo4jdb.egg-info/SOURCES.txt
neo4jdb.egg-info/dependency_links.txt
neo4jdb.egg-info/top_level.txt