Metadata-Version: 1.0
Name: neo4jdb
Version: 0.0.9
Summary: DB API 2.0 driver for the Neo4j graph database.
Home-page: https://github.com/jakewins/neo4jdb-python
Author: Jacob Hansson
Author-email: jakewins@gmail.com
License: UNKNOWN
Platform: UNKNOWN
Classifier: Programming Language :: Python :: 2.6
Classifier: Programming Language :: Python :: 2.7
Classifier: Programming Language :: Python :: 3.2
Classifier: Programming Language :: Python :: 3.3
